facleaning/Cleaning.py
facleaning/Data.py
facleaning/LanguageCheck.py
facleaning/__init__.py
facleaning-0.1.0.dist-info/METADATA
facleaning-0.1.0.dist-info/WHEEL
facleaning-0.1.0.dist-info/top_level.txt
facleaning-0.1.0.dist-info/RECORD
